CONSTANTS.py
bbsofa/__init__.py
bbsofa/augment/__init__.py
bbsofa/augment/_filaments_augmentation.py
bbsofa/cutouts/__init__.py
bbsofa/cutouts/_filament_cutouts.py
bbsofa/cutouts/filament_dataset.py
bbsofa/loader/__init__.py
bbsofa/loader/filament_data_loader.py
bbsofa/metadata/__init__.py
bbsofa/metadata/filament_metadata.py
bbsofa/transform/__init__.py
bbsofa/transform/_transformation.py
bbsofa/utils/__init__.py
bbsofa/utils/file_utilities.py
bbsofa/utils/image_utils.py
bbsofa/utils/timestamp_utilites.py
demo_fa-0.1.1.data/data/petdata/2015_chir_data.json
demo_fa-0.1.1.data/data/petdata/sample/08/01/bbso_halph_fl_20150801_174814.jpg
demo_fa-0.1.1.data/data/petdata/sample/08/01/bbso_halph_fl_20150801_203114.jpg
demo_fa-0.1.1.data/data/petdata/sample/08/01/bbso_halph_fr_20150801_174814.jpg
demo_fa-0.1.1.data/data/petdata/sample/08/01/bbso_halph_fr_20150801_203114.jpg
demo_fa-0.1.1.data/data/petdata/sample/08/01/gong_06768_fd_20150801_002203.jpg
demo_fa-0.1.1.data/data/petdata/sample/08/01/gong_06768_fd_20150801_012203.jpg
demo_fa-0.1.1.data/data/petdata/sample/08/01/gong_06768_fd_20150801_142103.jpg
demo_fa-0.1.1.data/data/petdata/sample/08/01/gong_06768_fd_20150801_152103.jpg
demo_fa-0.1.1.data/data/petdata/sample/08/01/gong_06768_fd_20150801_162103.jpg
demo_fa-0.1.1.data/data/petdata/sample/08/01/gong_06768_fd_20150801_172103.jpg
demo_fa-0.1.1.data/data/petdata/sample/08/01/gong_06768_fd_20150801_182103.jpg
demo_fa-0.1.1.data/data/petdata/sample/08/01/gong_06768_fd_20150801_192103.jpg
demo_fa-0.1.1.data/data/petdata/sample/08/01/gong_06768_fd_20150801_202103.jpg
demo_fa-0.1.1.data/data/petdata/sample/08/01/gong_06768_fd_20150801_212103.jpg
demo_fa-0.1.1.data/data/petdata/sample/08/01/gong_06768_fd_20150801_222103.jpg
demo_fa-0.1.1.data/data/petdata/sample/08/01/gong_06768_fd_20150801_232203.jpg
demo_fa-0.1.1.data/data/petdata/sample/08/01/gong_magxx_fd_20150801_002203.jpg
demo_fa-0.1.1.data/data/petdata/sample/08/01/gong_magxx_fd_20150801_012203.jpg
demo_fa-0.1.1.dist-info/LICENSE
demo_fa-0.1.1.dist-info/METADATA
demo_fa-0.1.1.dist-info/WHEEL
demo_fa-0.1.1.dist-info/top_level.txt
demo_fa-0.1.1.dist-info/RECORD
