Metadata-Version: 2.1
Name: demo-fa
Version: 0.1.1
Summary: Solar Filaments data augmentation demo package
Home-page: https://bitbucket.org/gsudmlab/bbso_fa/src/master/
Author: Shreejaa Talla
Author-email: shreejaa.talla@gmail.com
License: UNKNOWN
Project-URL: Source, https://bitbucket.org/gsudmlab/bbso_fa/src/master/
Platform: UNKNOWN
Classifier: Programming Language :: Python :: 3
Classifier: Operating System :: OS Independent
Classifier: License :: OSI Approved :: MIT License
License-File: LICENSE
Requires-Dist: sortedcontainers
Requires-Dist: opencv-python
Requires-Dist: torchvision
Requires-Dist: Pillow
